file_explorer_utils/FolderIterator.py
file_explorer_utils/IteratorFlow.py
file_explorer_utils/SmbIterator.py
file_explorer_utils/__init__.py
file_explorer_utils/folderUtils.py
file_explorer_utils/smbUtils.py
file_explorer_utils-2.0.0.dist-info/METADATA
file_explorer_utils-2.0.0.dist-info/WHEEL
file_explorer_utils-2.0.0.dist-info/top_level.txt
file_explorer_utils-2.0.0.dist-info/RECORD
